limecore/database/postgresql/__init__.py
limecore/database/postgresql/configuration.py
limecore/database/postgresql/database.py
limecore/database/postgresql/module.py
limecore/database/postgresql/result.py
limecore/database/postgresql/type_adapter.py
limecore/database/postgresql/type_adapters/__init__.py
limecore/database/postgresql/type_adapters/base_type_adapter.py
limecore/database/postgresql/type_adapters/default_type_adapter.py
limecore/database/postgresql/type_adapters/uuid_type_adapter.py
limecore_database_postgresql-0.1.0.dist-info/LICENSE.txt
limecore_database_postgresql-0.1.0.dist-info/METADATA
limecore_database_postgresql-0.1.0.dist-info/WHEEL
limecore_database_postgresql-0.1.0.dist-info/top_level.txt
limecore_database_postgresql-0.1.0.dist-info/RECORD
