Metadata-Version: 2.1
Name: limecore-database-postgresql
Version: 0.1.0
Summary: limecore: Database (PostgreSQL)
Home-page: https://github.com/limecore/database-postgresql
Author: Daniel Bradberry
Author-email: daniel@danielbradberry.com
License: MIT
Platform: UNKNOWN
Classifier: Programming Language :: Python :: 3
Classifier: License :: OSI Approved :: MIT License
Classifier: Operating System :: OS Independent
Requires-Python: >=3.7
Requires-Dist: injector
Requires-Dist: limecore-core (>=0.2.0)
Requires-Dist: limecore-database-api
Requires-Dist: limecore-logging
Requires-Dist: psycopg2
